pytest_google_chat/__init__.py
pytest_google_chat/config_manager.py
pytest_google_chat/plugin.py
pytest_google_chat/post_to_google_chat.py
pytest_google_chat-0.4.4.dist-info/LICENSE
pytest_google_chat-0.4.4.dist-info/METADATA
pytest_google_chat-0.4.4.dist-info/WHEEL
pytest_google_chat-0.4.4.dist-info/entry_points.txt
pytest_google_chat-0.4.4.dist-info/top_level.txt
pytest_google_chat-0.4.4.dist-info/RECORD
