Metadata-Version: 2.1
Name: pytest-google-chat
Version: 0.4.4
Summary: Notify google chat channel for test results
Home-page: https://github.com/geokats7/pytest-google-chat
Author: Yorgos Katsaros
Author-email: yorgos.katsaros@gmail.com
Maintainer: Yorgos Katsaros
Maintainer-email: yorgos.katsaros@gmail.com
License: MIT
Platform: UNKNOWN
Classifier: Development Status :: 4 - Beta
Classifier: Framework :: Pytest
Classifier: Intended Audience :: Developers
Classifier: Topic :: Software Development :: Testing
Classifier: Programming Language :: Python
Classifier: Programming Language :: Python :: 3 :: Only
Classifier: Operating System :: OS Independent
Classifier: License :: OSI Approved :: MIT License
Requires-Python: >=3.6
License-File: LICENSE
Requires-Dist: pytest
Requires-Dist: requests
